setup.py
asr_tools/__init__.py
asr_tools/evaluation.py
asr_tools/evaluation_util.py
asr_tools/kaldi.py
asr_tools/logging.py
asr_tools/nbest.py
asr_tools/nbest_util.py
asr_tools/reranking.py
asr_tools/scores.py
asr_tools/sentence.py
asr_tools/sentence_util.py
asr_tools.egg-info/PKG-INFO
asr_tools.egg-info/SOURCES.txt
asr_tools.egg-info/dependency_links.txt
asr_tools.egg-info/top_level.txt
test/test_main.py